pritunl_webclient/__init__.py
pritunl_webclient/client.py
pritunl_webclient/exceptions.py
pritunl_webclient/py.typed
pritunl_webclient-0.2.1.dist-info/METADATA
pritunl_webclient-0.2.1.dist-info/WHEEL
pritunl_webclient-0.2.1.dist-info/licenses/LICENSE
pritunl_webclient-0.2.1.dist-info/RECORD
