Metadata-Version: 2.4
Name: pritunl-webclient
Version: 0.2.1
Summary: Modern Python client for Pritunl Web API
Project-URL: Homepage, https://github.com/digglife/pritunl_webclient
Project-URL: Documentation, https://github.com/digglife/pritunl_webclient#readme
Project-URL: Repository, https://github.com/digglife/pritunl_webclient
Project-URL: Issues, https://github.com/digglife/pritunl_webclient/issues
Author-email: digglife <digglfe@gmai.com>
License: MIT
License-File: LICENSE
Keywords: api,pritunl,vpn
Classifier: Development Status :: 4 - Beta
Classifier: Intended Audience :: Developers
Classifier: License :: OSI Approved :: MIT License
Classifier: Operating System :: OS Independent
Classifier: Programming Language :: Python :: 3
Classifier: Programming Language :: Python :: 3.10
Classifier: Programming Language :: Python :: 3.11
Classifier: Programming Language :: Python :: 3.12
Classifier: Programming Language :: Python :: 3.13
Classifier: Topic :: Software Development :: Libraries :: Python Modules
Classifier: Topic :: System :: Networking
Requires-Python: >=3.10
Requires-Dist: httpx>=0.24.0
Provides-Extra: dev
Requires-Dist: mypy>=1.0.0; extra == 'dev'
Requires-Dist: pytest-cov>=4.0.0; extra == 'dev'
Requires-Dist: pytest>=7.0.0; extra == 'dev'
Requires-Dist: respx>=0.20.0; extra == 'dev'
Requires-Dist: ruff>=0.1.0; extra == 'dev'
